anemoi/training/__init__.py
anemoi/training/__main__.py
anemoi/training/_version.py
anemoi/training/commands/__init__.py
anemoi/training/commands/checkpoint.py
anemoi/training/commands/config.py
anemoi/training/commands/mlflow.py
anemoi/training/commands/profiler.py
anemoi/training/commands/train.py
anemoi/training/config/__init__.py
anemoi/training/config/config.yaml
anemoi/training/config/debug.yaml
anemoi/training/config/diffusion.yaml
anemoi/training/config/ensemble_crps.yaml
anemoi/training/config/hierarchical.yaml
anemoi/training/config/interpolator.yaml
anemoi/training/config/lam.yaml
anemoi/training/config/point_wise.yaml
anemoi/training/config/stretched.yaml
anemoi/training/config/data/zarr.yaml
anemoi/training/config/dataloader/native_grid.yaml
anemoi/training/config/diagnostics/evaluation.yaml
anemoi/training/config/diagnostics/evaluation_ens.yaml
anemoi/training/config/diagnostics/benchmark_profiler/detailed.yaml
anemoi/training/config/diagnostics/benchmark_profiler/simple.yaml
anemoi/training/config/diagnostics/callbacks/placeholder.yaml
anemoi/training/config/diagnostics/callbacks/rollout_eval.yaml
anemoi/training/config/diagnostics/plot/detailed.yaml
anemoi/training/config/diagnostics/plot/rollout_eval.yaml
anemoi/training/config/diagnostics/plot/simple.yaml
anemoi/training/config/graph/encoder_decoder_only.yaml
anemoi/training/config/graph/existing.yaml
anemoi/training/config/graph/existing_graph.yaml
anemoi/training/config/graph/hierarchical_2level.yaml
anemoi/training/config/graph/hierarchical_3level.yaml
anemoi/training/config/graph/limited_area.yaml
anemoi/training/config/graph/multi_scale.yaml
anemoi/training/config/graph/point_wise.yaml
anemoi/training/config/graph/stretched_grid.yaml
anemoi/training/config/model/gnn.yaml
anemoi/training/config/model/graphtransformer.yaml
anemoi/training/config/model/graphtransformer_diffusion.yaml
anemoi/training/config/model/graphtransformer_diffusiontend.yaml
anemoi_training-0.8.4.dist-info/licenses/LICENSE
anemoi_training-0.8.4.dist-info/METADATA
anemoi_training-0.8.4.dist-info/WHEEL
anemoi_training-0.8.4.dist-info/entry_points.txt
anemoi_training-0.8.4.dist-info/top_level.txt
anemoi_training-0.8.4.dist-info/RECORD
