Metadata-Version: 2.4
Name: anemoi-training
Version: 0.8.4
Summary: A package to hold various functions to support training of ML models.
Author-email: "European Centre for Medium-Range Weather Forecasts (ECMWF)" <software.support@ecmwf.int>
License:                                  Apache License
Project-URL: Changelog, https://github.com/ecmwf/anemoi-training/CHANGELOG.md
Project-URL: Documentation, https://anemoi-training.readthedocs.io/
Project-URL: Homepage, https://github.com/ecmwf/anemoi-training/
Project-URL: Issues, https://github.com/ecmwf/anemoi-training/issues
Project-URL: Repository, https://github.com/ecmwf/anemoi-training/
Keywords: ai,tools,training
Classifier: Development Status :: 4 - Beta
Classifier: Intended Audience :: Developers
Classifier: License :: OSI Approved :: Apache Software License
Classifier: Operating System :: OS Independent
Classifier: Programming Language :: Python :: 3 :: Only
Classifier: Programming Language :: Python :: 3.10
Classifier: Programming Language :: Python :: 3.11
Classifier: Programming Language :: Python :: 3.12
Classifier: Programming Language :: Python :: Implementation :: CPython
Classifier: Programming Language :: Python :: Implementation :: PyPy
Requires-Python: <3.13,>=3.10
License-File: LICENSE
Requires-Dist: anemoi-datasets>=0.5.13
Requires-Dist: anemoi-graphs>=0.5.2
Requires-Dist: anemoi-models[migrations]>=0.9.5
Requires-Dist: anemoi-transform>=0.1.11
Requires-Dist: anemoi-utils[mlflow,provenance]>=0.4.37
Requires-Dist: datashader<0.17,>=0.16.3; python_version < "3.10"
Requires-Dist: datashader>=0.17; python_version >= "3.10"
Requires-Dist: einops>=0.6.1
Requires-Dist: hydra-core>=1.3
Requires-Dist: matplotlib>=3.7.1
Requires-Dist: mlflow-skinny>=2.11.1
Requires-Dist: numpy
Requires-Dist: nvidia-ml-py>=13.580.82
Requires-Dist: pydantic>=2.9
Requires-Dist: pyshtools>=4.13
Requires-Dist: pytorch-lightning>=2.1
Requires-Dist: timm>=0.9.2
Requires-Dist: torch>=2.2
Requires-Dist: torch-geometric>=2.3.1
Requires-Dist: torchinfo>=1.8
Requires-Dist: torchvision>=0.18
Requires-Dist: tqdm>=4.65
Requires-Dist: zarr>=2.14.2
Provides-Extra: all
Provides-Extra: azure
Requires-Dist: azure-ai-ml; extra == "azure"
Requires-Dist: azure-identity; extra == "azure"
Requires-Dist: azureml-mlflow; extra == "azure"
Requires-Dist: strenum; extra == "azure"
Provides-Extra: dev
Requires-Dist: anemoi-training[all,docs,tests]; extra == "dev"
Requires-Dist: pre-commit>=3.3.3; extra == "dev"
Provides-Extra: docs
Requires-Dist: autodoc-pydantic; extra == "docs"
Requires-Dist: nbsphinx; extra == "docs"
Requires-Dist: pandoc; extra == "docs"
Requires-Dist: sphinx<8.2; python_version < "3.11" and extra == "docs"
Requires-Dist: sphinx>=8.2; python_version >= "3.11" and extra == "docs"
Requires-Dist: sphinx-argparse; extra == "docs"
Requires-Dist: sphinx-rtd-theme; extra == "docs"
Provides-Extra: plotting
Requires-Dist: distinctipy>=1; extra == "plotting"
Provides-Extra: profile
Requires-Dist: holistictraceanalysis>=0.2; extra == "profile"
Requires-Dist: pandas>=1.3.2; extra == "profile"
Requires-Dist: rich>=13.6; extra == "profile"
Requires-Dist: tabulate>=0.9; extra == "profile"
Provides-Extra: tests
Requires-Dist: anemoi-graphs[tri]; extra == "tests"
Requires-Dist: anemoi-training[azure]; extra == "tests"
Requires-Dist: hypothesis>=6.11; extra == "tests"
Requires-Dist: pytest>=8; extra == "tests"
Requires-Dist: pytest-mock>=3; extra == "tests"
Requires-Dist: pytest-skip-slow>=0.0.5; extra == "tests"
Requires-Dist: sshfs; extra == "tests"
Dynamic: license-file
